LICENSE
MANIFEST.in
README
ez_setup.py
ez_setup.pyc
setup.py
./socialnews/__init__.py
./socialnews/load.py
./socialnews/loadtest.py
./socialnews/manage.py
./socialnews/settings.py
./socialnews/urls.py
./socialnews/mptt/__init__.py
./socialnews/mptt/exceptions.py
./socialnews/mptt/forms.py
./socialnews/mptt/managers.py
./socialnews/mptt/models.py
./socialnews/mptt/signals.py
./socialnews/mptt/utils.py
./socialnews/mptt/templatetags/__init__.py
./socialnews/mptt/templatetags/mptt_tags.py
./socialnews/mptt/tests/__init__.py
./socialnews/mptt/tests/models.py
./socialnews/mptt/tests/settings.py
./socialnews/news/__init__.py
./socialnews/news/accounts.py
./socialnews/news/bforms.py
./socialnews/news/cron.py
./socialnews/news/defaults.py
./socialnews/news/exceptions.py
./socialnews/news/helpers.py
./socialnews/news/links.py
./socialnews/news/models.py
./socialnews/news/rss.py
./socialnews/news/scraping.py
./socialnews/news/search.py
./socialnews/news/static.py
./socialnews/news/subscriptions.py
./socialnews/news/tags.py
./socialnews/news/tapicks_middleware.py
./socialnews/news/tests.py
./socialnews/news/topics.py
./socialnews/news/users.py
./socialnews/news/views.py
./socialnews/news/libs/__init__.py
./socialnews/news/libs/redditstories.py
./socialnews/news/libs/sqllogmiddleware.py
django_socialnews.egg-info/PKG-INFO
django_socialnews.egg-info/SOURCES.txt
django_socialnews.egg-info/dependency_links.txt
django_socialnews.egg-info/not-zip-safe
django_socialnews.egg-info/top_level.txt
socialnews/__init__.py
socialnews/load.py
socialnews/loadtest.py
socialnews/manage.py
socialnews/settings.py
socialnews/urls.py
socialnews/mptt/__init__.py
socialnews/mptt/exceptions.py
socialnews/mptt/forms.py
socialnews/mptt/managers.py
socialnews/mptt/models.py
socialnews/mptt/signals.py
socialnews/mptt/utils.py
socialnews/mptt/templatetags/__init__.py
socialnews/mptt/templatetags/mptt_tags.py
socialnews/mptt/tests/__init__.py
socialnews/mptt/tests/models.py
socialnews/mptt/tests/settings.py
socialnews/news/__init__.py
socialnews/news/accounts.py
socialnews/news/bforms.py
socialnews/news/cron.py
socialnews/news/defaults.py
socialnews/news/exceptions.py
socialnews/news/helpers.py
